__init__.py
gerent.py
gerent-0.0.2.dist-info/LICENSE
gerent-0.0.2.dist-info/METADATA
gerent-0.0.2.dist-info/WHEEL
gerent-0.0.2.dist-info/top_level.txt
gerent-0.0.2.dist-info/RECORD
