Metadata-Version: 2.1
Name: gerent
Version: 0.0.2
Summary: A simple and lightweight MicroPython web-framework
Author-email: Tomasz Jarko <tomasz.jarko@gmail.com>
Maintainer-email: Tomasz Jarko <tomasz.jarko@gmail.com>
Project-URL: Homepage, https://github.com/Tomson601/gerent
Project-URL: Bug Tracker, https://github.com/Tomson601/gerent/issues
Classifier: Programming Language :: Python :: 3
Classifier: License :: OSI Approved :: MIT License
Classifier: Operating System :: OS Independent
Requires-Python: >=3.7
License-File: LICENSE
